fastepoll/__init__.py
fastepoll/fastepoll.cpython-311-x86_64-linux-gnu.so
fastepoll-1.0.1.dist-info/LICENSE.txt
fastepoll-1.0.1.dist-info/METADATA
fastepoll-1.0.1.dist-info/WHEEL
fastepoll-1.0.1.dist-info/top_level.txt
fastepoll-1.0.1.dist-info/RECORD
