Metadata-Version: 2.1
Name: fastepoll
Version: 1.0.1
Summary: Fast asyncio and uvloop-replacement for Linux servers using multiprocess epoll and shared memory
Author: Source61
License: Copyright (C) SymbalSoft A/S
Project-URL: GitHub, https://github.com/source61/fastepoll
Project-URL: Changelogs, https://github.com/source61/fastepoll/CHANGELOGS.md
Classifier: Programming Language :: Python :: 3.11
Classifier: Programming Language :: Python :: 3 :: Only
License-File: LICENSE.txt
Requires-Dist: importlib-metadata; python_version == "3.11"
